MammothAnalytics/__init__.py
MammothAnalytics/const.py
MammothAnalytics/errors.py
MammothAnalytics/mammoth.py
MammothAnalytics/urls.py
MammothAnalytics/utils.py
mammoth_analytics_sdk-1.7.2.dist-info/METADATA
mammoth_analytics_sdk-1.7.2.dist-info/WHEEL
mammoth_analytics_sdk-1.7.2.dist-info/top_level.txt
mammoth_analytics_sdk-1.7.2.dist-info/RECORD
