Metadata-Version: 2.1
Name: mammoth-analytics-sdk
Version: 1.7.2
Summary: Python client for Mammoth Analytics (https://mammoth.io)
Author: Mammoth developer
Author-email: developer@mammoth.io
Requires-Dist: requests
Requires-Dist: pytest
Requires-Dist: names
Requires-Dist: pydash ==6.0.2
